LICENSE
MANIFEST.in
README.rst
pyproject.toml
setup.cfg
setup.py
cffi/build.py
cffi/cdefs.h
cffi/source.c
sysrepo/__init__.py
sysrepo/change.py
sysrepo/connection.py
sysrepo/errors.py
sysrepo/py.typed
sysrepo/session.py
sysrepo/subscription.py
sysrepo/util.py
sysrepo/value.py
sysrepo.egg-info/PKG-INFO
sysrepo.egg-info/SOURCES.txt
sysrepo.egg-info/dependency_links.txt
sysrepo.egg-info/not-zip-safe
sysrepo.egg-info/requires.txt
sysrepo.egg-info/top_level.txt
tests/test_connection.py
tests/test_session.py
tests/test_subs_module_change.py
tests/test_subs_notification.py
tests/test_subs_oper.py
tests/test_subs_rpc.py