Metadata-Version: 2.4
Name: sysrepo
Version: 1.7.6
Summary: Sysrepo CFFI bindings
Home-page: https://www.6wind.com/
Author: Robin Jarry
Author-email: robin.jarry@6wind.com
License: BSD 3 clause
Keywords: sysrepo,libyang,cffi
Classifier: Development Status :: 4 - Beta
Classifier: Environment :: Console
Classifier: Intended Audience :: Developers
Classifier: License :: OSI Approved :: BSD License
Classifier: Operating System :: Unix
Classifier: Programming Language :: Python :: 3
Classifier: Topic :: Software Development :: Libraries
Requires-Python: >=3.6
License-File: LICENSE
Requires-Dist: libyang>=2.1
Requires-Dist: cffi; platform_python_implementation != "PyPy"
Dynamic: author
Dynamic: author-email
Dynamic: classifier
Dynamic: description
Dynamic: home-page
Dynamic: keywords
Dynamic: license
Dynamic: license-file
Dynamic: requires-dist
Dynamic: requires-python
Dynamic: summary
